phill/__init__.py
phill/py.typed
phill/PySide6/QtCore.py
phill/PySide6/QtGui.py
phill/PySide6/QtWidgets.py
phill/PySide6/__init__.py
phill/pytest/__init__.py
phill/pytest/PySide6/QtCore.py
phill/pytest/PySide6/QtGui.py
phill/pytest/PySide6/QtWidgets.py
phill/pytest/PySide6/__init__.py
phill-0.1.1.dist-info/LICENSE.txt
phill-0.1.1.dist-info/METADATA
phill-0.1.1.dist-info/WHEEL
phill-0.1.1.dist-info/entry_points.txt
phill-0.1.1.dist-info/top_level.txt
phill-0.1.1.dist-info/RECORD
