Metadata-Version: 2.1
Name: phill
Version: 0.1.1
Summary: Fills missing functionalities in dependencies
Home-page: UNKNOWN
Author: Boni Lindsley
Author-email: boni@lindsley.xyz
License: UNKNOWN
Platform: UNKNOWN
Classifier: License :: OSI Approved :: MIT License
Classifier: Programming Language :: Python :: 3
Requires-Python: >=3.9
License-File: LICENSE.txt
Provides-Extra: pyside6
Requires-Dist: PySide6 (>=6.2.2.1) ; extra == 'pyside6'
Provides-Extra: dev
Requires-Dist: Sphinx (>=4.2.0) ; extra == 'dev'
Requires-Dist: black (>=21.9b0) ; extra == 'dev'
Requires-Dist: coverage[toml] (>=6.0.2) ; extra == 'dev'
Requires-Dist: mypy (>=0.910) ; extra == 'dev'
Requires-Dist: pytest (>=6.2.5) ; extra == 'dev'
Requires-Dist: tox (>=3.24.4) ; extra == 'dev'
